romeways_memory_queue/__init__.py
romeways_memory_queue/config/__init__.py
romeways_memory_queue/config/connector/__init__.py
romeways_memory_queue/config/connector/model.py
romeways_memory_queue/config/queue/__init__.py
romeways_memory_queue/config/queue/model.py
romeways_memory_queue/infrastructure/__init__.py
romeways_memory_queue/infrastructure/connector/__init__.py
romeways_memory_queue/infrastructure/connector/infrastructure.py
romeways_memory_queue-0.2.0.dist-info/LICENSE
romeways_memory_queue-0.2.0.dist-info/METADATA
romeways_memory_queue-0.2.0.dist-info/WHEEL
romeways_memory_queue-0.2.0.dist-info/RECORD
