Metadata-Version: 2.1
Name: romeways-memory-queue
Version: 0.2.0
Summary: 
Author: Marco Sievers de Almeida Ximit Gaia
Author-email: im.ximit@gmail.com
Requires-Python: >=3.11,<4.0
Classifier: Programming Language :: Python :: 3
Classifier: Programming Language :: Python :: 3.11
